async_easy_utils/__init__.py
async_easy_utils/utils.py
async_easy_utils/serializer/__init__.py
async_easy_utils/serializer/exceptions.py
async_easy_utils/serializer/fields.py
async_easy_utils/serializer/validators.py
async_easy_utils/view/__init__.py
async_easy_utils/view/validators.py
tests/__init__.py
tests/fixtures.py
tests/helpers.py
tests/tests.py
async_easy_utils-0.1.3.dist-info/LICENSE
async_easy_utils-0.1.3.dist-info/METADATA
async_easy_utils-0.1.3.dist-info/WHEEL
async_easy_utils-0.1.3.dist-info/top_level.txt
async_easy_utils-0.1.3.dist-info/RECORD
