Metadata-Version: 2.1
Name: async-easy-utils
Version: 0.1.3
Summary: REST tools for building backends with TorToiseORM and Starlette framework
Home-page: https://www.github.com/t1waz/rest_utils
Author: t1waz
Author-email: milewiczmichal87@gmail.com
License: MIT
Platform: UNKNOWN
Classifier: Programming Language :: Python :: 3
Classifier: License :: OSI Approved :: MIT License
Classifier: Operating System :: OS Independent
Requires-Python: >=3.6
Requires-Dist: aiosqlite (==0.13.0)
Requires-Dist: ciso8601 (==2.1.3)
Requires-Dist: coverage (==5.1)
Requires-Dist: entrypoints (==0.3)
Requires-Dist: flake8 (==3.7.9)
Requires-Dist: mccabe (==0.6.1)
Requires-Dist: pycodestyle (==2.5.0)
Requires-Dist: pyflakes (==2.1.1)
Requires-Dist: PyPika (==0.37.6)
Requires-Dist: starlette (==0.13.4)
Requires-Dist: tortoise-orm (==0.16.13)
Requires-Dist: typing-extensions (==3.7.4.2)
